MANIFEST.in
README.rst
README.txt
project.ini
requirements.txt
setup.py
aioviber/__init__.py
aioviber/api.py
aioviber/app.py
aioviber/bot.py
aioviber/chat.py
aioviber/eventtype.py
aioviber/keyboard.py
aioviber/messagetype.py
aioviber/middleware.py
aioviber/setup_logging.py
aioviber/test_api.py
aioviber.egg-info/PKG-INFO
aioviber.egg-info/SOURCES.txt
aioviber.egg-info/dependency_links.txt
aioviber.egg-info/requires.txt
aioviber.egg-info/top_level.txt