Metadata-Version: 1.0
Name: aioviber
Version: 0.1.5
Summary: Asynchronous Python API for building Viber bots.
Home-page: https://github.com/nonamenix/aioviber.git
Author: nonamenix
Author-email: nonamenix@gmail.com
License: UNKNOWN
Platform: UNKNOWN
